inferio_x/__init__.py
inferio_x/_background.py
inferio_x/_configs.py
inferio_x/_endpoint.py
inferio_x/_exceptions.py
inferio_x/_file.py
inferio_x/_log.py
inferio_x/_method.py
inferio_x/_response.py
inferio_x/_service.py
inferio_x/_utils.py
inferio_x-0.1.1.dist-info/METADATA
inferio_x-0.1.1.dist-info/WHEEL
inferio_x-0.1.1.dist-info/RECORD
