Metadata-Version: 2.1
Name: inferio-x
Version: 0.1.1
Summary: 
Home-page: https://github.com/portmind/inferio-x
Author: Portmind's ML Engineering Team
Maintainer: Sevak Harutyunyan
Maintainer-email: sevak.harutyunyan@portmind.com
Requires-Python: >=3.8,<4.0
Classifier: Operating System :: OS Independent
Classifier: Programming Language :: Python :: 3
Classifier: Programming Language :: Python :: 3.8
Classifier: Programming Language :: Python :: 3.9
Classifier: Programming Language :: Python :: 3.10
Classifier: Programming Language :: Python :: 3.11
Classifier: Programming Language :: Python :: 3.12
Provides-Extra: fileupload
Requires-Dist: httpx (>=0.27,<0.28)
Requires-Dist: orjson (>=3.10,<3.11)
Requires-Dist: pydantic (>=2.7,<2.8)
Requires-Dist: python-multipart (>=0.0.5,<0.0.6) ; extra == "fileupload"
Requires-Dist: starlette (>=0.37,<0.38)
Requires-Dist: starlette-exporter (>=0.21,<0.22)
Requires-Dist: uvicorn (>=0.29,<0.30)
Project-URL: Repository, https://github.com/portmind/inferio-x
